{
	"textures": [
		{
			"image": "environment-sd-0.png",
			"format": "RGBA8888",
			"size": {
				"w": 449,
				"h": 491
			},
			"scale": 0.125,
			"frames": [
				{
					"filename": "Trees/Tree1",
					"rotated": false,
					"trimmed": true,
					"sourceSize": {
						"w": 221,
						"h": 217
					},
					"spriteSourceSize": {
						"x": 6,
						"y": 0,
						"w": 215,
						"h": 179
					},
					"frame": {
						"x": 10,
						"y": 10,
						"w": 215,
						"h": 179
					},
					"anchor": {
						"x": 0.63554,
						"y": 0.772203
					}
				},
				{
					"filename": "Trees/Tree",
					"rotated": false,
					"trimmed": true,
					"sourceSize": {
						"w": 214,
						"h": 221
					},
					"spriteSourceSize": {
						"x": 20,
						"y": 2,
						"w": 193,
						"h": 184
					},
					"frame": {
						"x": 243,
						"y": 10,
						"w": 193,
						"h": 184
					},
					"anchor": {
						"x": 0.6021,
						"y": 0.800792
					}
				},
				{
					"filename": "Trees/Tree2",
					"rotated": false,
					"trimmed": true,
					"sourceSize": {
						"w": 163,
						"h": 200
					},
					"spriteSourceSize": {
						"x": 2,
						"y": 7,
						"w": 143,
						"h": 164
					},
					"frame": {
						"x": 10,
						"y": 207,
						"w": 143,
						"h": 164
					},
					"anchor": {
						"x": 0.502308,
						"y": 0.8225
					}
				},
				{
					"filename": "Tiles/base00",
					"rotated": false,
					"trimmed": false,
					"sourceSize": {
						"w": 64,
						"h": 37
					},
					"spriteSourceSize": {
						"x": 0,
						"y": 0,
						"w": 64,
						"h": 37
					},
					"frame": {
						"x": 10,
						"y": 389,
						"w": 64,
						"h": 37
					},
					"anchor": {
						"x": 0.5,
						"y": 0.5
					}
				},
				{
					"filename": "Tiles/base01",
					"rotated": false,
					"trimmed": false,
					"sourceSize": {
						"w": 64,
						"h": 37
					},
					"spriteSourceSize": {
						"x": 0,
						"y": 0,
						"w": 64,
						"h": 37
					},
					"frame": {
						"x": 10,
						"y": 389,
						"w": 64,
						"h": 37
					},
					"anchor": {
						"x": 0.5,
						"y": 0.5
					}
				},
				{
					"filename": "Tiles/base03",
					"rotated": false,
					"trimmed": false,
					"sourceSize": {
						"w": 64,
						"h": 37
					},
					"spriteSourceSize": {
						"x": 0,
						"y": 0,
						"w": 64,
						"h": 37
					},
					"frame": {
						"x": 10,
						"y": 389,
						"w": 64,
						"h": 37
					},
					"anchor": {
						"x": 0.5,
						"y": 0.5
					}
				},
				{
					"filename": "Tiles/base02",
					"rotated": false,
					"trimmed": false,
					"sourceSize": {
						"w": 64,
						"h": 37
					},
					"spriteSourceSize": {
						"x": 0,
						"y": 0,
						"w": 64,
						"h": 37
					},
					"frame": {
						"x": 10,
						"y": 444,
						"w": 64,
						"h": 37
					},
					"anchor": {
						"x": 0.5,
						"y": 0.5
					}
				},
				{
					"filename": "Tiles/base02bef",
					"rotated": false,
					"trimmed": false,
					"sourceSize": {
						"w": 64,
						"h": 37
					},
					"spriteSourceSize": {
						"x": 0,
						"y": 0,
						"w": 64,
						"h": 37
					},
					"frame": {
						"x": 92,
						"y": 389,
						"w": 64,
						"h": 37
					},
					"anchor": {
						"x": 0.5,
						"y": 0.5
					}
				},
				{
					"filename": "Tiles/base04",
					"rotated": false,
					"trimmed": false,
					"sourceSize": {
						"w": 64,
						"h": 37
					},
					"spriteSourceSize": {
						"x": 0,
						"y": 0,
						"w": 64,
						"h": 37
					},
					"frame": {
						"x": 92,
						"y": 444,
						"w": 64,
						"h": 37
					},
					"anchor": {
						"x": 0.5,
						"y": 0.5
					}
				},
				{
					"filename": "Trees/PineTree",
					"rotated": false,
					"trimmed": true,
					"sourceSize": {
						"w": 153,
						"h": 213
					},
					"spriteSourceSize": {
						"x": 19,
						"y": 19,
						"w": 104,
						"h": 152
					},
					"frame": {
						"x": 171,
						"y": 212,
						"w": 104,
						"h": 152
					},
					"anchor": {
						"x": 0.492647,
						"y": 0.764706
					}
				},
				{
					"filename": "Cliffs/cliff2",
					"rotated": false,
					"trimmed": true,
					"sourceSize": {
						"w": 64,
						"h": 106
					},
					"spriteSourceSize": {
						"x": 0,
						"y": 7,
						"w": 64,
						"h": 99
					},
					"frame": {
						"x": 174,
						"y": 382,
						"w": 64,
						"h": 99
					},
					"anchor": {
						"x": 0.5,
						"y": 0.17411764705882352
					}
				},
				{
					"filename": "Cliffs/cliff1",
					"rotated": false,
					"trimmed": true,
					"sourceSize": {
						"w": 64,
						"h": 100
					},
					"spriteSourceSize": {
						"x": 0,
						"y": 1,
						"w": 64,
						"h": 96
					},
					"frame": {
						"x": 256,
						"y": 382,
						"w": 64,
						"h": 96
					},
					"anchor": {
						"x": 0.5,
						"y": 0.185
					}
				},
				{
					"filename": "Cliffs/cliff3",
					"rotated": false,
					"trimmed": true,
					"sourceSize": {
						"w": 64,
						"h": 106
					},
					"spriteSourceSize": {
						"x": 0,
						"y": 3,
						"w": 64,
						"h": 103
					},
					"frame": {
						"x": 293,
						"y": 212,
						"w": 64,
						"h": 103
					},
					"anchor": {
						"x": 0.5,
						"y": 0.17411764705882352
					}
				},
				{
					"filename": "Tiles/grass00",
					"rotated": false,
					"trimmed": false,
					"sourceSize": {
						"w": 64,
						"h": 37
					},
					"spriteSourceSize": {
						"x": 0,
						"y": 0,
						"w": 64,
						"h": 37
					},
					"frame": {
						"x": 338,
						"y": 333,
						"w": 64,
						"h": 37
					},
					"anchor": {
						"x": 0.5,
						"y": 0.5
					}
				},
				{
					"filename": "Tiles/grass01",
					"rotated": false,
					"trimmed": false,
					"sourceSize": {
						"w": 64,
						"h": 37
					},
					"spriteSourceSize": {
						"x": 0,
						"y": 0,
						"w": 64,
						"h": 37
					},
					"frame": {
						"x": 375,
						"y": 212,
						"w": 64,
						"h": 37
					},
					"anchor": {
						"x": 0.5,
						"y": 0.5
					}
				},
				{
					"filename": "Tiles/grass02",
					"rotated": false,
					"trimmed": false,
					"sourceSize": {
						"w": 64,
						"h": 37
					},
					"spriteSourceSize": {
						"x": 0,
						"y": 0,
						"w": 64,
						"h": 37
					},
					"frame": {
						"x": 375,
						"y": 267,
						"w": 64,
						"h": 37
					},
					"anchor": {
						"x": 0.5,
						"y": 0.5
					}
				},
				{
					"filename": "Tiles/grass03",
					"rotated": false,
					"trimmed": false,
					"sourceSize": {
						"w": 64,
						"h": 37
					},
					"spriteSourceSize": {
						"x": 0,
						"y": 0,
						"w": 64,
						"h": 37
					},
					"frame": {
						"x": 338,
						"y": 388,
						"w": 64,
						"h": 37
					},
					"anchor": {
						"x": 0.5,
						"y": 0.5
					}
				},
				{
					"filename": "Tiles/grass04",
					"rotated": false,
					"trimmed": false,
					"sourceSize": {
						"w": 64,
						"h": 37
					},
					"spriteSourceSize": {
						"x": 0,
						"y": 0,
						"w": 64,
						"h": 37
					},
					"frame": {
						"x": 338,
						"y": 443,
						"w": 64,
						"h": 37
					},
					"anchor": {
						"x": 0.5,
						"y": 0.5
					}
				}
			]
		}
	],
	"meta": {
		"app": "https://www.codeandweb.com/texturepacker",
		"version": "3.0",
		"smartupdate": "$TexturePacker:SmartUpdate:b2766b253b2be064e3087568f04e8b5d:b41c9cf9662d3ea967fc13489b03e4b8:1efd645e775df4ac353f239e5fd118d6$"
	}
}
